{
    "name": "Global Information",
    "numberOfRequests": {
        "total": 7,
        "ok": 7,
        "ko": 0
    },
    "minResponseTime": {
        "total": 172,
        "ok": 172,
        "ko": 0
    },
    "maxResponseTime": {
        "total": 1143,
        "ok": 1143,
        "ko": 0
    },
    "meanResponseTime": {
        "total": 581,
        "ok": 581,
        "ko": 0
    },
    "standardDeviation": {
        "total": 276,
        "ok": 276,
        "ko": 0
    },
    "percentiles1": {
        "total": 574,
        "ok": 574,
        "ko": 0
    },
    "percentiles2": {
        "total": 636,
        "ok": 636,
        "ko": 0
    },
    "percentiles3": {
        "total": 994,
        "ok": 994,
        "ko": 0
    },
    "percentiles4": {
        "total": 1113,
        "ok": 1113,
        "ko": 0
    },
    "group1": {
        "name": "t < 800 ms",
        "count": 6,
        "percentage": 86
    },
    "group2": {
        "name": "800 ms < t < 1200 ms",
        "count": 1,
        "percentage": 14
    },
    "group3": {
        "name": "t > 1200 ms",
        "count": 0,
        "percentage": 0
    },
    "group4": {
        "name": "failed",
        "count": 0,
        "percentage": 0
    },
    "meanNumberOfRequestsPerSecond": {
        "total": 1.75,
        "ok": 1.75,
        "ko": 0
    }
}